{"columns":[{"name":"modelVersion","type":{"isPrimitive":true,"inputString":"string"}},{"name":"event_type","type":{"isPrimitive":true,"inputString":"string"}},{"name":"event_timestamp","type":{"isPrimitive":true,"inputString":"string"}},{"name":"arrival_timestamp","type":{"isPrimitive":true,"inputString":"int"}},{"name":"event_version","type":{"isPrimitive":true,"inputString":"string"}},{"name":"application","type":{"isPrimitive":false,"inputString":"struct<id:string>"}},{"name":"client","type":{"isPrimitive":false,"inputString":"struct<id:string>"}},{"name":"device","type":{"isPrimitive":false,"inputString":"struct<useragent:string>"}},{"name":"session","type":{"isPrimitive":false,"inputString":"struct<id:string>"}},{"name":"attributes","type":{"isPrimitive":false,"inputString":"array<struct<type:string,name:string,stringValue:string,stringValues:array<string>,numValue:float,numValues:array<float>>>"}},{"name":"endpoint","type":{"isPrimitive":false,"inputString":"struct<id:string>"}},{"name":"awsAccountId","type":{"isPrimitive":true,"inputString":"string"}},{"name":"userId","type":{"isPrimitive":true,"inputString":"string"}}]}